ckanext/__init__.py
ckanext/attribution/__init__.py
ckanext/attribution/plugin.py
ckanext/attribution/commands/__init__.py
ckanext/attribution/commands/cli.py
ckanext/attribution/commands/migration/__init__.py
ckanext/attribution/commands/migration/api_search.py
ckanext/attribution/commands/migration/combiner.py
ckanext/attribution/commands/migration/common.py
ckanext/attribution/commands/migration/parser.py
ckanext/attribution/lib/__init__.py
ckanext/attribution/lib/helpers.py
ckanext/attribution/lib/orcid_api.py
ckanext/attribution/lib/ror_api.py
ckanext/attribution/logic/__init__.py
ckanext/attribution/logic/actions/__init__.py
ckanext/attribution/logic/actions/create.py
ckanext/attribution/logic/actions/delete.py
ckanext/attribution/logic/actions/extra.py
ckanext/attribution/logic/actions/helpers.py
ckanext/attribution/logic/actions/show.py
ckanext/attribution/logic/actions/update.py
ckanext/attribution/logic/actions/meta/__init__.py
ckanext/attribution/logic/actions/meta/help.py
ckanext/attribution/logic/actions/meta/schema.py
ckanext/attribution/logic/auth/__init__.py
ckanext/attribution/logic/auth/create.py
ckanext/attribution/logic/auth/delete.py
ckanext/attribution/logic/auth/extra.py
ckanext/attribution/logic/auth/show.py
ckanext/attribution/logic/auth/update.py
ckanext/attribution/model/__init__.py
ckanext/attribution/model/agent.py
ckanext/attribution/model/agent_affiliation.py
ckanext/attribution/model/agent_contribution_activity.py
ckanext/attribution/model/contribution_activity.py
ckanext/attribution/model/package_contribution_activity.py
ckanext/attribution/model/relationships.py
ckanext/attribution/model/crud/__init__.py
ckanext/attribution/model/crud/_base.py
ckanext/attribution/model/crud/agent.py
ckanext/attribution/model/crud/agent_affiliation.py
ckanext/attribution/model/crud/agent_contribution_activity.py
ckanext/attribution/model/crud/contribution_activity.py
ckanext/attribution/model/crud/package.py
ckanext_attribution-1.2.14.dist-info/licenses/LICENSE
ckanext_attribution-1.2.14.dist-info/METADATA
ckanext_attribution-1.2.14.dist-info/WHEEL
ckanext_attribution-1.2.14.dist-info/entry_points.txt
ckanext_attribution-1.2.14.dist-info/top_level.txt
ckanext_attribution-1.2.14.dist-info/RECORD
