Metadata-Version: 2.4
Name: ckanext-attribution
Version: 1.2.14
Summary: A CKAN extension that adds support for complex attribution.
Author-email: Natural History Museum <data@nhm.ac.uk>
License: GPL-3.0-or-later
Project-URL: repository, https://github.com/NaturalHistoryMuseum/ckanext-attribution
Project-URL: changelog, https://github.com/NaturalHistoryMuseum/ckanext-attribution/blob/main/CHANGELOG.md
Keywords: CKAN,data,attribution
Classifier: Development Status :: 5 - Production/Stable
Classifier: License :: OSI Approved :: GNU General Public License v3 (GPLv3)
Classifier: Programming Language :: Python
Classifier: Programming Language :: Python :: 3 :: Only
Classifier: Programming Language :: Python :: 3.6
Classifier: Programming Language :: Python :: 3.7
Classifier: Programming Language :: Python :: 3.8
Requires-Python: >=3.6
License-File: LICENSE
Requires-Dist: orcid~=1.0
Requires-Dist: sqlalchemy
Requires-Dist: requests
Requires-Dist: fuzzywuzzy[speedup]
Requires-Dist: ckantools>=0.4.2
Provides-Extra: test
Requires-Dist: mock; extra == "test"
Requires-Dist: pytest>=4.6.5; extra == "test"
Requires-Dist: pytest-cov>=2.7.1; extra == "test"
Requires-Dist: coveralls; extra == "test"
Provides-Extra: cli
Requires-Dist: spacy[transformers]~=3.7.0; extra == "cli"
Requires-Dist: unidecode~=1.0; extra == "cli"
Requires-Dist: nameparser~=1.0; extra == "cli"
Requires-Dist: prompt_toolkit~=3.0; extra == "cli"
Dynamic: license-file
